promptlibz/__init__.py
promptlibz/cli.py
promptlibz/core.py
promptlibz-1.0.2.dist-info/METADATA
promptlibz-1.0.2.dist-info/WHEEL
promptlibz-1.0.2.dist-info/top_level.txt
promptlibz-1.0.2.dist-info/RECORD
