Metadata-Version: 2.4
Name: promptlibz
Version: 1.0.2
Summary: 用来存储优质prompt的仓库
Requires-Python: >=3.10
Requires-Dist: dill>=0.4.0
Requires-Dist: llama-index==0.12.30
Requires-Dist: pyyaml>=6.0.2
Requires-Dist: toml==0.10.2
